{
  "info": {
    "description": "data",
    "version": "1.0",
    "year": 2025,
    "contributor": "search engine",
    "source": "augmented",
    "license": {
      "name": "Creative Commons Attribution 4.0 International",
      "url": "https://creativecommons.org/licenses/by/4.0/"
    }
  },
  "images": [
    {
      "id": 8422681357,
      "width": 640,
      "height": 640,
      "file_name": "DSC_1411_12kv4r16k_8.jpg",
      "size": 74986,
      "format": "JPEG",
      "url": "",
      "hash": "",
      "status": "success"
    }
  ],
  "annotations": [
    {
      "id": 401631357,
      "image_id": 8422681357,
      "category_id": 5168985379,
      "segmentation": [],
      "area": 2953.6213663744,
      "bbox": [
        372.72064,
        4.40896,
        50.59456,
        58.378240000000005
      ],
      "iscrowd": 0
    },
    {
      "id": 401631358,
      "image_id": 8422681357,
      "category_id": 5168985379,
      "segmentation": [],
      "area": 1513.5111331839998,
      "bbox": [
        0.0,
        199.0016,
        31.50208,
        48.044799999999995
      ],
      "iscrowd": 0
    },
    {
      "id": 401631359,
      "image_id": 8422681357,
      "category_id": 5168985379,
      "segmentation": [],
      "area": 2553.504804864,
      "bbox": [
        192.72639999999998,
        294.30048,
        47.6736,
        53.56224
      ],
      "iscrowd": 0
    },
    {
      "id": 401631360,
      "image_id": 8422681357,
      "category_id": 5168985379,
      "segmentation": [],
      "area": 1713.4663684095997,
      "bbox": [
        181.05056000000002,
        369.74048000000005,
        45.72736,
        37.47136
      ],
      "iscrowd": 0
    },
    {
      "id": 401631361,
      "image_id": 8422681357,
      "category_id": 5168985379,
      "segmentation": [],
      "area": 1711.9900848128002,
      "bbox": [
        83.73024,
        376.37280000000004,
        38.96384,
        43.937920000000005
      ],
      "iscrowd": 0
    },
    {
      "id": 401631362,
      "image_id": 8422681357,
      "category_id": 5168985379,
      "segmentation": [],
      "area": 2165.9652562944,
      "bbox": [
        26.34944,
        431.53695999999997,
        50.59456,
        42.81024000000001
      ],
      "iscrowd": 0
    },
    {
      "id": 401631363,
      "image_id": 8422681357,
      "category_id": 5168985379,
      "segmentation": [],
      "area": 1496.386584576,
      "bbox": [
        341.58592,
        608.61184,
        47.6736,
        31.38816
      ],
      "iscrowd": 0
    },
    {
      "id": 401631364,
      "image_id": 8422681357,
      "category_id": 5168985379,
      "segmentation": [],
      "area": 3016.057376768,
      "bbox": [
        388.28959999999995,
        540.50624,
        57.404799999999994,
        52.54016
      ],
      "iscrowd": 0
    },
    {
      "id": 401631365,
      "image_id": 8422681357,
      "category_id": 5168985379,
      "segmentation": [],
      "area": 1643.1887761408002,
      "bbox": [
        517.3056,
        489.91328,
        42.222080000000005,
        38.91776
      ],
      "iscrowd": 0
    },
    {
      "id": 401631366,
      "image_id": 8422681357,
      "category_id": 5168985379,
      "segmentation": [],
      "area": 3399.4196504576,
      "bbox": [
        338.66656,
        286.56672000000003,
        61.29728,
        55.457919999999994
      ],
      "iscrowd": 0
    },
    {
      "id": 401631367,
      "image_id": 8422681357,
      "category_id": 5168985379,
      "segmentation": [],
      "area": 3393.0234920959997,
      "bbox": [
        581.96896,
        193.16224,
        50.52992,
        67.1488
      ],
      "iscrowd": 0
    }
  ],
  "categories": [
    {
      "id": 5168985379,
      "name": "pear640",
      "supercategory": "pear"
    }
  ]
}