{
  "info": {
    "description": "data",
    "version": "1.0",
    "year": 2025,
    "contributor": "search engine",
    "source": "augmented",
    "license": {
      "name": "Creative Commons Attribution 4.0 International",
      "url": "https://creativecommons.org/licenses/by/4.0/"
    }
  },
  "images": [
    {
      "id": 7931084356,
      "width": 640,
      "height": 640,
      "file_name": "DSC_1394_12kv3r23k_8.jpg",
      "size": 78553,
      "format": "JPEG",
      "url": "",
      "hash": "",
      "status": "success"
    }
  ],
  "annotations": [
    {
      "id": 9936417356,
      "image_id": 7931084356,
      "category_id": 5168985379,
      "segmentation": [],
      "area": 3364.3785785344003,
      "bbox": [
        568.14432,
        206.52768,
        60.83392,
        55.304320000000004
      ],
      "iscrowd": 0
    },
    {
      "id": 9936417357,
      "image_id": 7931084356,
      "category_id": 5168985379,
      "segmentation": [],
      "area": 2107.2986226688,
      "bbox": [
        524.76672,
        119.37856,
        46.14016,
        45.671679999999995
      ],
      "iscrowd": 0
    },
    {
      "id": 9936417358,
      "image_id": 7931084356,
      "category_id": 5168985379,
      "segmentation": [],
      "area": 1515.9045152768,
      "bbox": [
        609.9724799999999,
        30.87008,
        30.027520000000003,
        50.48384
      ],
      "iscrowd": 0
    },
    {
      "id": 9936417359,
      "image_id": 7931084356,
      "category_id": 5168985379,
      "segmentation": [],
      "area": 1261.9776720896,
      "bbox": [
        617.9174399999999,
        47.987840000000006,
        22.08256,
        57.14816
      ],
      "iscrowd": 0
    },
    {
      "id": 9936417360,
      "image_id": 7931084356,
      "category_id": 5168985379,
      "segmentation": [],
      "area": 1298.927271936,
      "bbox": [
        335.75104,
        69.63712,
        37.3056,
        34.81856
      ],
      "iscrowd": 0
    },
    {
      "id": 9936417361,
      "image_id": 7931084356,
      "category_id": 5168985379,
      "segmentation": [],
      "area": 3057.6476749824,
      "bbox": [
        357.98400000000004,
        271.97312000000005,
        56.22528,
        54.38208
      ],
      "iscrowd": 0
    },
    {
      "id": 9936417362,
      "image_id": 7931084356,
      "category_id": 5168985379,
      "segmentation": [],
      "area": 2275.5147382784,
      "bbox": [
        255.91231999999997,
        252.73664,
        41.23648,
        55.18208
      ],
      "iscrowd": 0
    },
    {
      "id": 9936417363,
      "image_id": 7931084356,
      "category_id": 5168985379,
      "segmentation": [],
      "area": 1303.7693964288,
      "bbox": [
        300.83552000000003,
        272.74656,
        36.57408,
        35.64736
      ],
      "iscrowd": 0
    },
    {
      "id": 9936417364,
      "image_id": 7931084356,
      "category_id": 5168985379,
      "segmentation": [],
      "area": 2566.714755072,
      "bbox": [
        3.1139200000000002,
        439.73024,
        52.540800000000004,
        48.851839999999996
      ],
      "iscrowd": 0
    },
    {
      "id": 9936417365,
      "image_id": 7931084356,
      "category_id": 5168985379,
      "segmentation": [],
      "area": 1477.3422452736,
      "bbox": [
        269.8608,
        78.69728,
        35.87008,
        41.185919999999996
      ],
      "iscrowd": 0
    },
    {
      "id": 9936417366,
      "image_id": 7931084356,
      "category_id": 5168985379,
      "segmentation": [],
      "area": 1334.8325302271999,
      "bbox": [
        299.75552,
        94.64032,
        36.535039999999995,
        36.53568
      ],
      "iscrowd": 0
    },
    {
      "id": 9936417367,
      "image_id": 7931084356,
      "category_id": 5168985379,
      "segmentation": [],
      "area": 1632.9466920959999,
      "bbox": [
        0.8291200000000032,
        121.86560000000001,
        36.4768,
        44.76672
      ],
      "iscrowd": 0
    }
  ],
  "categories": [
    {
      "id": 5168985379,
      "name": "pear640",
      "supercategory": "pear"
    }
  ]
}