{
  "info": {
    "description": "data",
    "version": "1.0",
    "year": 2025,
    "contributor": "search engine",
    "source": "augmented",
    "license": {
      "name": "Creative Commons Attribution 4.0 International",
      "url": "https://creativecommons.org/licenses/by/4.0/"
    }
  },
  "images": [
    {
      "id": 126075357,
      "width": 640,
      "height": 640,
      "file_name": "DSC_1403_12kv4r8k_10.jpg",
      "size": 71013,
      "format": "JPEG",
      "url": "",
      "hash": "",
      "status": "success"
    }
  ],
  "annotations": [
    {
      "id": 5794137357,
      "image_id": 126075357,
      "category_id": 5168985379,
      "segmentation": [],
      "area": 3134.1365821440004,
      "bbox": [
        401.68351999999993,
        245.38816,
        51.788160000000005,
        60.5184
      ],
      "iscrowd": 0
    },
    {
      "id": 5794137358,
      "image_id": 126075357,
      "category_id": 5168985379,
      "segmentation": [],
      "area": 3686.8741074943996,
      "bbox": [
        414.33056,
        202.28,
        71.99936,
        51.20704
      ],
      "iscrowd": 0
    },
    {
      "id": 5794137359,
      "image_id": 126075357,
      "category_id": 5168985379,
      "segmentation": [],
      "area": 2229.9986460672,
      "bbox": [
        480.8288,
        203.86496,
        44.76672,
        49.81376
      ],
      "iscrowd": 0
    },
    {
      "id": 5794137360,
      "image_id": 126075357,
      "category_id": 5168985379,
      "segmentation": [],
      "area": 2848.5992460288,
      "bbox": [
        465.90688,
        295.32320000000004,
        53.88607999999999,
        52.86336
      ],
      "iscrowd": 0
    },
    {
      "id": 5794137361,
      "image_id": 126075357,
      "category_id": 5168985379,
      "segmentation": [],
      "area": 2587.0509699072,
      "bbox": [
        354.98015999999996,
        258.65312,
        53.51232,
        48.34496
      ],
      "iscrowd": 0
    },
    {
      "id": 5794137362,
      "image_id": 126075357,
      "category_id": 5168985379,
      "segmentation": [],
      "area": 1721.2824838144,
      "bbox": [
        248.70495999999997,
        199.79264,
        35.25184,
        48.82816
      ],
      "iscrowd": 0
    },
    {
      "id": 5794137363,
      "image_id": 126075357,
      "category_id": 5168985379,
      "segmentation": [],
      "area": 2405.7260728319998,
      "bbox": [
        203.20032000000003,
        246.6752,
        49.64928,
        48.4544
      ],
      "iscrowd": 0
    },
    {
      "id": 5794137364,
      "image_id": 126075357,
      "category_id": 5168985379,
      "segmentation": [],
      "area": 1602.2929162240005,
      "bbox": [
        218.85984,
        310.89024,
        43.937920000000005,
        36.467200000000005
      ],
      "iscrowd": 0
    },
    {
      "id": 5794137365,
      "image_id": 126075357,
      "category_id": 5168985379,
      "segmentation": [],
      "area": 1992.9826197503999,
      "bbox": [
        168.28992,
        301.16096000000005,
        45.59616,
        43.70944
      ],
      "iscrowd": 0
    },
    {
      "id": 5794137366,
      "image_id": 126075357,
      "category_id": 5168985379,
      "segmentation": [],
      "area": 3407.488507904,
      "bbox": [
        49.74079999999999,
        232.95327999999998,
        55.54432,
        61.3472
      ],
      "iscrowd": 0
    },
    {
      "id": 5794137367,
      "image_id": 126075357,
      "category_id": 5168985379,
      "segmentation": [],
      "area": 3152.2026590208,
      "bbox": [
        121.47296000000001,
        218.4592,
        43.78176,
        71.99808
      ],
      "iscrowd": 0
    },
    {
      "id": 5794137368,
      "image_id": 126075357,
      "category_id": 5168985379,
      "segmentation": [],
      "area": 3322.8246597632,
      "bbox": [
        64.06848,
        276.83583999999996,
        63.243520000000004,
        52.54016
      ],
      "iscrowd": 0
    },
    {
      "id": 5794137369,
      "image_id": 126075357,
      "category_id": 5168985379,
      "segmentation": [],
      "area": 3599.8268522496,
      "bbox": [
        45.59552,
        142.59072,
        60.30976,
        59.68896
      ],
      "iscrowd": 0
    },
    {
      "id": 5794137370,
      "image_id": 126075357,
      "category_id": 5168985379,
      "segmentation": [],
      "area": 2917.8972831744,
      "bbox": [
        97.14944,
        128.94783999999999,
        45.44128,
        64.21248
      ],
      "iscrowd": 0
    },
    {
      "id": 5794137371,
      "image_id": 126075357,
      "category_id": 5168985379,
      "segmentation": [],
      "area": 2348.5456896,
      "bbox": [
        253.79232,
        32.62688,
        43.824,
        53.5904
      ],
      "iscrowd": 0
    },
    {
      "id": 5794137372,
      "image_id": 126075357,
      "category_id": 5168985379,
      "segmentation": [],
      "area": 2251.4837065727997,
      "bbox": [
        169.14720000000003,
        51.398720000000004,
        44.75583999999999,
        50.30592
      ],
      "iscrowd": 0
    },
    {
      "id": 5794137373,
      "image_id": 126075357,
      "category_id": 5168985379,
      "segmentation": [],
      "area": 2590.0002164735993,
      "bbox": [
        136.06655999999998,
        49.16704,
        46.702079999999995,
        55.457919999999994
      ],
      "iscrowd": 0
    },
    {
      "id": 5794137374,
      "image_id": 126075357,
      "category_id": 5168985379,
      "segmentation": [],
      "area": 2380.0031231999997,
      "bbox": [
        213.90336,
        70.5712,
        51.38176,
        46.31999999999999
      ],
      "iscrowd": 0
    },
    {
      "id": 5794137375,
      "image_id": 126075357,
      "category_id": 5168985379,
      "segmentation": [],
      "area": 1259.2014835711998,
      "bbox": [
        213.90336000000002,
        121.8656,
        38.94656,
        32.33152
      ],
      "iscrowd": 0
    },
    {
      "id": 5794137376,
      "image_id": 126075357,
      "category_id": 5168985379,
      "segmentation": [],
      "area": 2993.0656710655994,
      "bbox": [
        211.39872,
        187.35744,
        53.88607999999999,
        55.54432
      ],
      "iscrowd": 0
    },
    {
      "id": 5794137377,
      "image_id": 126075357,
      "category_id": 5168985379,
      "segmentation": [],
      "area": 2192.409280512,
      "bbox": [
        120.20736,
        265.28512,
        45.59616,
        48.083200000000005
      ],
      "iscrowd": 0
    },
    {
      "id": 5794137378,
      "image_id": 126075357,
      "category_id": 5168985379,
      "segmentation": [],
      "area": 678.3324004351999,
      "bbox": [
        29.844480000000004,
        158.34207999999998,
        17.40928,
        38.96384
      ],
      "iscrowd": 0
    }
  ],
  "categories": [
    {
      "id": 5168985379,
      "name": "pear640",
      "supercategory": "pear"
    }
  ]
}