{
  "info": {
    "description": "data",
    "version": "1.0",
    "year": 2025,
    "contributor": "search engine",
    "source": "augmented",
    "license": {
      "name": "Creative Commons Attribution 4.0 International",
      "url": "https://creativecommons.org/licenses/by/4.0/"
    }
  },
  "images": [
    {
      "id": 7457903356,
      "width": 640,
      "height": 640,
      "file_name": "DSC_1394_12kv3r23k_2.jpg",
      "size": 78140,
      "format": "JPEG",
      "url": "",
      "hash": "",
      "status": "success"
    }
  ],
  "annotations": [
    {
      "id": 9183672356,
      "image_id": 7457903356,
      "category_id": 5168985379,
      "segmentation": [],
      "area": 3345.89626368,
      "bbox": [
        483.28224,
        125.41504,
        54.748799999999996,
        61.113600000000005
      ],
      "iscrowd": 0
    },
    {
      "id": 9183672357,
      "image_id": 7457903356,
      "category_id": 5168985379,
      "segmentation": [],
      "area": 2634.9763018751996,
      "bbox": [
        461.76192,
        141.7616,
        44.76672,
        58.86015999999999
      ],
      "iscrowd": 0
    }
  ],
  "categories": [
    {
      "id": 5168985379,
      "name": "pear640",
      "supercategory": "pear"
    }
  ]
}