{
  "info": {
    "description": "data",
    "version": "1.0",
    "year": 2025,
    "contributor": "search engine",
    "source": "augmented",
    "license": {
      "name": "Creative Commons Attribution 4.0 International",
      "url": "https://creativecommons.org/licenses/by/4.0/"
    }
  },
  "images": [
    {
      "id": 9014617356,
      "width": 640,
      "height": 640,
      "file_name": "DSC_1384_12kv3r12k_5.jpg",
      "size": 86043,
      "format": "JPEG",
      "url": "",
      "hash": "",
      "status": "success"
    }
  ],
  "annotations": [
    {
      "id": 7620308356,
      "image_id": 9014617356,
      "category_id": 5168985379,
      "segmentation": [],
      "area": 1536.4796719104002,
      "bbox": [
        40.611200000000004,
        309.98240000000004,
        38.14528,
        40.279680000000006
      ],
      "iscrowd": 0
    },
    {
      "id": 7620308357,
      "image_id": 9014617356,
      "category_id": 5168985379,
      "segmentation": [],
      "area": 2081.966841856,
      "bbox": [
        32.331199999999995,
        402.90175999999997,
        38.0512,
        54.71488
      ],
      "iscrowd": 0
    },
    {
      "id": 7620308358,
      "image_id": 9014617356,
      "category_id": 5168985379,
      "segmentation": [],
      "area": 2010.4584421376,
      "bbox": [
        75.63584000000002,
        402.8022399999999,
        40.280319999999996,
        49.911680000000004
      ],
      "iscrowd": 0
    },
    {
      "id": 7620308359,
      "image_id": 9014617356,
      "category_id": 5168985379,
      "segmentation": [],
      "area": 2447.4771263488005,
      "bbox": [
        158.824,
        248.68640000000002,
        49.03616,
        49.911680000000004
      ],
      "iscrowd": 0
    },
    {
      "id": 7620308360,
      "image_id": 9014617356,
      "category_id": 5168985379,
      "segmentation": [],
      "area": 1127.1912685568,
      "bbox": [
        2.956800000000001,
        552.53888,
        30.64832,
        36.778240000000004
      ],
      "iscrowd": 0
    },
    {
      "id": 7620308361,
      "image_id": 9014617356,
      "category_id": 5168985379,
      "segmentation": [],
      "area": 1288.2141085696,
      "bbox": [
        51.993280000000006,
        512.2592,
        36.77888,
        35.02592
      ],
      "iscrowd": 0
    },
    {
      "id": 7620308362,
      "image_id": 9014617356,
      "category_id": 5168985379,
      "segmentation": [],
      "area": 1349.4539878399999,
      "bbox": [
        56.37152000000001,
        476.35776,
        35.025279999999995,
        38.528
      ],
      "iscrowd": 0
    },
    {
      "id": 7620308363,
      "image_id": 9014617356,
      "category_id": 5168985379,
      "segmentation": [],
      "area": 858.7414089728,
      "bbox": [
        58.997440000000005,
        545.5350400000001,
        35.025279999999995,
        24.517760000000003
      ],
      "iscrowd": 0
    },
    {
      "id": 7620308364,
      "image_id": 9014617356,
      "category_id": 5168985379,
      "segmentation": [],
      "area": 1012.0904908799998,
      "bbox": [
        30.102080000000008,
        549.03808,
        35.025279999999995,
        28.896
      ],
      "iscrowd": 0
    },
    {
      "id": 7620308365,
      "image_id": 9014617356,
      "category_id": 5168985379,
      "segmentation": [],
      "area": 644.0521338880001,
      "bbox": [
        51.117760000000004,
        577.93312,
        26.2688,
        24.517760000000003
      ],
      "iscrowd": 0
    },
    {
      "id": 7620308366,
      "image_id": 9014617356,
      "category_id": 5168985379,
      "segmentation": [],
      "area": 886.4196194304,
      "bbox": [
        37.98304,
        598.07392,
        29.77344,
        29.77216
      ],
      "iscrowd": 0
    },
    {
      "id": 7620308367,
      "image_id": 9014617356,
      "category_id": 5168985379,
      "segmentation": [],
      "area": 1394.1556199423997,
      "bbox": [
        2.9571199999999997,
        606.83008,
        42.030719999999995,
        33.16992
      ],
      "iscrowd": 0
    },
    {
      "id": 7620308368,
      "image_id": 9014617356,
      "category_id": 5168985379,
      "segmentation": [],
      "area": 2223.5485175808,
      "bbox": [
        100.15424000000002,
        500.0,
        43.78112,
        50.787839999999996
      ],
      "iscrowd": 0
    },
    {
      "id": 7620308369,
      "image_id": 9014617356,
      "category_id": 5168985379,
      "segmentation": [],
      "area": 2061.0251108352,
      "bbox": [
        136.93280000000001,
        493.86976,
        42.030719999999995,
        49.03616
      ],
      "iscrowd": 0
    },
    {
      "id": 7620308370,
      "image_id": 9014617356,
      "category_id": 5168985379,
      "segmentation": [],
      "area": 2442.97150464,
      "bbox": [
        185.96800000000002,
        535.90176,
        47.28576,
        51.664
      ],
      "iscrowd": 0
    },
    {
      "id": 7620308371,
      "image_id": 9014617356,
      "category_id": 5168985379,
      "segmentation": [],
      "area": 1320.4382920704,
      "bbox": [
        151.81663999999998,
        533.2751999999999,
        36.77888,
        35.90208
      ],
      "iscrowd": 0
    },
    {
      "id": 7620308372,
      "image_id": 9014617356,
      "category_id": 5168985379,
      "segmentation": [],
      "area": 2525.8010247168,
      "bbox": [
        202.60544000000002,
        436.07616,
        47.28576,
        53.415679999999995
      ],
      "iscrowd": 0
    },
    {
      "id": 7620308373,
      "image_id": 9014617356,
      "category_id": 5168985379,
      "segmentation": [],
      "area": 3307.1884697600003,
      "bbox": [
        250.36288,
        436.95296,
        51.1936,
        64.6016
      ],
      "iscrowd": 0
    },
    {
      "id": 7620308374,
      "image_id": 9014617356,
      "category_id": 5168985379,
      "segmentation": [],
      "area": 2094.2364119040003,
      "bbox": [
        300.68127999999996,
        556.2691199999999,
        42.906240000000004,
        48.8096
      ],
      "iscrowd": 0
    },
    {
      "id": 7620308375,
      "image_id": 9014617356,
      "category_id": 5168985379,
      "segmentation": [],
      "area": 1348.7924600832002,
      "bbox": [
        365.59583999999995,
        212.78400000000002,
        26.528640000000003,
        50.84288
      ],
      "iscrowd": 0
    },
    {
      "id": 7620308376,
      "image_id": 9014617356,
      "category_id": 5168985379,
      "segmentation": [],
      "area": 2275.3749774336,
      "bbox": [
        479.31231999999994,
        113.57536,
        51.66272,
        44.042880000000004
      ],
      "iscrowd": 0
    },
    {
      "id": 7620308377,
      "image_id": 9014617356,
      "category_id": 5168985379,
      "segmentation": [],
      "area": 2043.6519354368002,
      "bbox": [
        527.47392,
        105.28512,
        40.401920000000004,
        50.58304
      ],
      "iscrowd": 0
    },
    {
      "id": 7620308378,
      "image_id": 9014617356,
      "category_id": 5168985379,
      "segmentation": [],
      "area": 2193.0703654912004,
      "bbox": [
        512.5884799999999,
        163.74687999999998,
        45.535360000000004,
        48.16192
      ],
      "iscrowd": 0
    },
    {
      "id": 7620308379,
      "image_id": 9014617356,
      "category_id": 5168985379,
      "segmentation": [],
      "area": 2124.1272729599996,
      "bbox": [
        551.992,
        171.6064,
        44.89919999999999,
        47.3088
      ],
      "iscrowd": 0
    },
    {
      "id": 7620308380,
      "image_id": 9014617356,
      "category_id": 5168985379,
      "segmentation": [],
      "area": 1470.2507122688,
      "bbox": [
        604.5324800000001,
        202.2768,
        35.46752,
        41.45344
      ],
      "iscrowd": 0
    }
  ],
  "categories": [
    {
      "id": 5168985379,
      "name": "pear640",
      "supercategory": "pear"
    }
  ]
}